snip_dedup/__init__.py
snip_dedup/cli.py
snip_dedup/snip_compress.py
snip_dedup/snip_download.py
snip_dedup/snip_index.py
snip_dedup-0.0.4.dist-info/METADATA
snip_dedup-0.0.4.dist-info/WHEEL
snip_dedup-0.0.4.dist-info/entry_points.txt
snip_dedup-0.0.4.dist-info/licenses/LICENSE
snip_dedup-0.0.4.dist-info/RECORD
