Metadata-Version: 2.1
Name: snip-dedup
Version: 0.0.4
Summary: SNIP: compact index for large dataset
Project-URL: Documentation, https://github.com/ryanwebster90/snip-dedup#readme
Project-URL: Source, https://github.com/ryanwebster90/snip-dedup
Author-email: Ryan Webster <rwebstr@gmail.com>, Matthieu Pizenberg <matthieu.pizenberg@gmail.com>
License-Expression: MIT
License-File: LICENSE
Keywords: computer vision,dataset,deduplicate,index,laion,machine learning,snip
Classifier: Environment :: GPU :: NVIDIA CUDA
Classifier: License :: OSI Approved :: MIT License
Classifier: Programming Language :: Python :: 3
Classifier: Topic :: Scientific/Engineering :: Artificial Intelligence
Requires-Python: >=3.8
Requires-Dist: fastparquet===2023.2.0
Requires-Dist: fire==0.5.*
Requires-Dist: numpy<2.0,>=1.24.2
Requires-Dist: pandas<2.0,>=1.5.3
Requires-Dist: requests<3.0,>=2.28.2
